mqpipeline/__init__.py
mqpipeline/config.py
mqpipeline/pipeline.py
mqpipeline-0.1.0.dist-info/licenses/LICENSE
mqpipeline-0.1.0.dist-info/METADATA
mqpipeline-0.1.0.dist-info/WHEEL
mqpipeline-0.1.0.dist-info/top_level.txt
mqpipeline-0.1.0.dist-info/RECORD
