Metadata-Version: 2.4
Name: mqpipeline
Version: 0.1.0
Summary: A reusable RabbitMQ pipeline handler for publishing and consuming messages.
Home-page: https://github.com/kazimsarikaya/mqpipeline
Author: Kazım SARIKAYA
License: MIT
Classifier: Programming Language :: Python :: 3
Classifier: Programming Language :: Python :: 3.8
Classifier: Programming Language :: Python :: 3.9
Classifier: Programming Language :: Python :: 3.10
Classifier: Programming Language :: Python :: 3.11
Classifier: Programming Language :: Python :: 3.12
Classifier: Operating System :: OS Independent
Requires-Python: >=3.8
License-File: LICENSE
Requires-Dist: pika
Requires-Dist: pydantic
Requires-Dist: pydantic-settings
Dynamic: author
Dynamic: classifier
Dynamic: description
Dynamic: description-content-type
Dynamic: home-page
Dynamic: license
Dynamic: license-file
Dynamic: requires-dist
Dynamic: requires-python
Dynamic: summary
